ZtjDirImport.py
dir_import-0.0.3.dist-info/METADATA
dir_import-0.0.3.dist-info/WHEEL
dir_import-0.0.3.dist-info/top_level.txt
dir_import-0.0.3.dist-info/RECORD
